iris_grib/__init__.py
iris_grib/_grib1_load_rules.py
iris_grib/_grib_cf_map.py
iris_grib/_load_convert.py
iris_grib/_save_rules.py
iris_grib/_version.py
iris_grib/message.py
iris_grib/grib_phenom_translation/__init__.py
iris_grib/grib_phenom_translation/_gribcode.py
iris_grib/tests/__init__.py
iris_grib/tests/test_license_headers.py
iris_grib/tests/integration/__init__.py
iris_grib/tests/integration/format_interop/__init__.py
iris_grib/tests/integration/format_interop/test_name_grib.py
iris_grib/tests/integration/format_interop/test_pp_grib.py
iris_grib/tests/integration/iris_integration/__init__.py
iris_grib/tests/integration/iris_integration/test_callback.py
iris_grib/tests/integration/iris_integration/test_pickle_message.py
iris_grib/tests/integration/load_convert/__init__.py
iris_grib/tests/integration/load_convert/test_data_section.py
iris_grib/tests/integration/load_convert/test_load_hybrid_coords.py
iris_grib/tests/integration/load_convert/test_product_definition_section.py
iris_grib/tests/integration/load_convert/test_sample_file_loads.py
iris_grib/tests/integration/round_trip/__init__.py
iris_grib/tests/integration/round_trip/test_WAFC_mapping_round_trip.py
iris_grib/tests/integration/round_trip/test_grid_definition_section.py
iris_grib/tests/integration/round_trip/test_hybrid_coords_round_trip.py
iris_grib/tests/integration/round_trip/test_product_definition_section.py
iris_grib/tests/integration/save_rules/__init__.py
iris_grib/tests/integration/save_rules/test_grib_save.py
iris_grib/tests/integration/save_rules/test_grid_definition_section.py
iris_grib/tests/integration/save_rules/test_save_hybrid_coords.py
iris_grib/tests/results/integration/iris_integration/callback/TestCallbacks/load_callback.cml
iris_grib/tests/results/integration/load_convert/data_section/TestDRT3/grid_complex_spatial_differencing.cml
iris_grib/tests/results/integration/load_convert/data_section/TestDRT3/grid_complex_spatial_differencing.data.0.json
iris_grib-0.21.0.dist-info/LICENSE
iris_grib-0.21.0.dist-info/METADATA
iris_grib-0.21.0.dist-info/WHEEL
iris_grib-0.21.0.dist-info/top_level.txt
iris_grib-0.21.0.dist-info/RECORD
