Metadata-Version: 2.1
Name: iris-grib
Version: 0.21.0
Summary: Functionality for converting between weather/climate datasets stored as GRIB files and SciTools-Iris Cubes
Author-email: Iris-grib Contributors <scitools.pub@gmail.com>
License: BSD-3-Clause
Project-URL: Code, https://github.com/SciTools/iris-grib
Project-URL: Discussions, https://github.com/SciTools/iris-grib/discussions
Project-URL: Documentation, https://iris-grib.readthedocs.io/en/stable/
Project-URL: Issues, https://github.com/SciTools/iris-grib/issues
Keywords: iris,GRIB,data-analysis,earth-science,meteorology
Classifier: Development Status :: 5 - Production/Stable
Classifier: Intended Audience :: Science/Research
Classifier: License :: OSI Approved :: BSD License
Classifier: Operating System :: MacOS
Classifier: Operating System :: POSIX
Classifier: Operating System :: POSIX :: Linux
Classifier: Operating System :: Unix
Classifier: Programming Language :: Python
Classifier: Programming Language :: Python :: 3 :: Only
Classifier: Programming Language :: Python :: 3.10
Classifier: Programming Language :: Python :: 3.11
Classifier: Programming Language :: Python :: 3.12
Classifier: Programming Language :: Python :: Implementation :: CPython
Classifier: Topic :: Scientific/Engineering
Classifier: Topic :: Scientific/Engineering :: Atmospheric Science
Classifier: Topic :: Scientific/Engineering :: Visualization
Requires-Python: >=3.10
License-File: LICENSE
Requires-Dist: scitools-iris>=3.0.2
Requires-Dist: eccodes>=1.6.1
Provides-Extra: dev
Requires-Dist: mo_pack; extra == "dev"
Requires-Dist: pre-commit; extra == "dev"
Provides-Extra: test
Requires-Dist: codecov; extra == "test"
Requires-Dist: filelock; extra == "test"
Requires-Dist: nox; extra == "test"
Requires-Dist: requests; extra == "test"
Requires-Dist: iris-sample-data; extra == "test"
Requires-Dist: pytest; extra == "test"
Requires-Dist: pytest-cov; extra == "test"
Requires-Dist: pytest-mock; extra == "test"
